postfix_logsums/__init__.py
postfix_logsums/app.py
postfix_logsums/errors.py
postfix_logsums/results.py
postfix_logsums/stats.py
postfix_logsums/xlate.py
postfix_logsums-0.9.4.data/scripts/postfix-logsums
usr/local/share/locale/de/LC_MESSAGES/postfix_logsums.mo
usr/local/share/locale/en/LC_MESSAGES/postfix_logsums.mo
postfix_logsums-0.9.4.dist-info/LICENSE
postfix_logsums-0.9.4.dist-info/METADATA
postfix_logsums-0.9.4.dist-info/WHEEL
postfix_logsums-0.9.4.dist-info/top_level.txt
postfix_logsums-0.9.4.dist-info/RECORD
