Metadata-Version: 2.1
Name: postfix-logsums
Version: 0.9.4
Summary: Produce Postfix MTA logfile summary
Home-page: https://github.com/pixelpark/postfix-logsums
Author: Frank Brehm
Author-email: frank@brehm-online.com
License: LGPL3+
Platform: posix
Classifier: Development Status :: 3 - Alpha
Classifier: Environment :: Console
Classifier: Intended Audience :: Developers
Classifier: Intended Audience :: System Administrators
Classifier: License :: OSI Approved :: GNU Lesser General Public License v3 or later (LGPLv3+)
Classifier: Natural Language :: English
Classifier: Operating System :: POSIX
Classifier: Programming Language :: Python :: 3.6
Classifier: Programming Language :: Python :: 3.7
Classifier: Programming Language :: Python :: 3.8
Classifier: Programming Language :: Python :: 3.9
Classifier: Programming Language :: Python :: 3.10
Classifier: Programming Language :: Python :: 3.11
Classifier: Topic :: Communications :: Email :: Mail Transport Agents
Classifier: Topic :: Software Development :: Libraries :: Python Modules
Classifier: Topic :: System :: Systems Administration
Requires: packaging
Requires: setuptools
Requires: wheel
Requires: Babel
Requires: PyYAML
Provides: postfix_logsums
License-File: LICENSE
